pyoverkiz/__init__.py
pyoverkiz/client.py
pyoverkiz/const.py
pyoverkiz/exceptions.py
pyoverkiz/models.py
pyoverkiz/obfuscate.py
pyoverkiz/overkiz-root-ca-2048.crt
pyoverkiz/py.typed
pyoverkiz/types.py
pyoverkiz/utils.py
pyoverkiz/enums/__init__.py
pyoverkiz/enums/command.py
pyoverkiz/enums/execution.py
pyoverkiz/enums/gateway.py
pyoverkiz/enums/general.py
pyoverkiz/enums/measured_value_type.py
pyoverkiz/enums/protocol.py
pyoverkiz/enums/server.py
pyoverkiz/enums/state.py
pyoverkiz/enums/ui.py
pyoverkiz-1.20.0.dist-info/METADATA
pyoverkiz-1.20.0.dist-info/WHEEL
pyoverkiz-1.20.0.dist-info/licenses/LICENSE
pyoverkiz-1.20.0.dist-info/RECORD
