Metadata-Version: 2.4
Name: pyoverkiz
Version: 1.20.0
Summary: Async Python client to interact with internal OverKiz API (e.g. used by Somfy TaHoma).
Project-URL: homepage, https://github.com/iMicknl/python-overkiz-api
Project-URL: repository, https://github.com/iMicknl/python-overkiz-api
Author: Vincent Le Bourlot, Thibaut Etienne
Author-email: Mick Vleeshouwer <mick@imick.nl>
License: MIT
License-File: LICENSE
Requires-Python: <4.0,>=3.10
Requires-Dist: aiohttp<4.0.0,>=3.10.3
Requires-Dist: attrs>=21.2
Requires-Dist: backoff<3.0,>=1.10.0
Requires-Dist: backports-strenum<2.0.0,>=1.2.4; python_version < '3.11'
Requires-Dist: boto3<2.0.0,>=1.18.59
Requires-Dist: pyhumps<4.0.0,>=3.8.0
Requires-Dist: warrant-lite<2.0.0,>=1.0.4
